ckanext/__init__.py
ckanext/wysiwyg/__init__.py
ckanext/wysiwyg/helpers.py
ckanext/wysiwyg/plugin.py
ckanext/wysiwyg/utils.py
ckanext/wysiwyg/views.py
ckanext/wysiwyg/assets/webassets.yml
ckanext/wysiwyg/assets/css/ckeditor5-custom-styles.css
ckanext/wysiwyg/assets/css/summernote-custom-styles.css
ckanext/wysiwyg/assets/css/vendor/ckeditor5.min.css
ckanext/wysiwyg/assets/css/vendor/quill.min.css
ckanext/wysiwyg/assets/css/vendor/summernote.min.css
ckanext/wysiwyg/assets/js/wysiwyg-ckeditor5-init.js
ckanext/wysiwyg/assets/js/wysiwyg-summernote-init.js
ckanext/wysiwyg/assets/js/vendor/ckeditor5.min.js
ckanext/wysiwyg/assets/js/vendor/summernote.min.js
ckanext/wysiwyg/logic/__init__.py
ckanext/wysiwyg/logic/validators.py
ckanext/wysiwyg/public/font/summernote.ttf
ckanext/wysiwyg/public/font/summernote.woff
ckanext/wysiwyg/public/font/summernote.woff2
ckanext/wysiwyg/templates/page.html
ckanext/wysiwyg/templates/scheming/display_snippets/wysiwyg_ckeditor5.html
ckanext/wysiwyg/templates/scheming/display_snippets/wysiwyg_summernote.html
ckanext/wysiwyg/templates/scheming/form_snippets/wysiwyg_ckeditor5.html
ckanext/wysiwyg/templates/scheming/form_snippets/wysiwyg_summernote.html
ckanext/wysiwyg/tests/__init__.py
ckanext/wysiwyg/tests/test_plugin.py
ckanext_wysiwyg-0.2.25.dist-info/LICENSE
ckanext_wysiwyg-0.2.25.dist-info/METADATA
ckanext_wysiwyg-0.2.25.dist-info/WHEEL
ckanext_wysiwyg-0.2.25.dist-info/entry_points.txt
ckanext_wysiwyg-0.2.25.dist-info/top_level.txt
ckanext_wysiwyg-0.2.25.dist-info/RECORD
